pkhpc1pyr/P2L1.py
pkhpc1pyr/P2L2.py
pkhpc1pyr/P2L3.py
pkhpc1pyr/__init__.py
pkhpc1pyr/tests/TestP2L1.py
pkhpc1pyr/tests/TestP2L2.py
pkhpc1pyr/tests/TestP2L3.py
pkhpc1pyr/tests/__init__.py
pkhpc1pyr/utils/P2L1Err.py
pkhpc1pyr/utils/P2L1Plot.py
pkhpc1pyr/utils/P2L2Err.py
pkhpc1pyr/utils/P2L2Plot.py
pkhpc1pyr/utils/P2L3Err.py
pkhpc1pyr/utils/P2L3Plot.py
pkhpc1pyr/utils/__init__.py
pkhpc1pyr/utils/helperFunctions.py
pkhpc1pyr-0.0.4.dist-info/METADATA
pkhpc1pyr-0.0.4.dist-info/WHEEL
pkhpc1pyr-0.0.4.dist-info/licenses/LICENSE
pkhpc1pyr-0.0.4.dist-info/RECORD
