Metadata-Version: 2.1
Name: pkhpc1pyr
Version: 0.0.4
Summary: Scripts and functions for the pharmacokinetic modeling of hyperpolarized [1-13C]-pyruvate.
Project-URL: Homepage, https://github.com/RytyB/HP-C1Pyr-PK-Python
Author-email: Ryan Boyce <ryty.boyce@gmail.com>
License-File: LICENSE
Classifier: License :: OSI Approved :: MIT License
Classifier: Operating System :: OS Independent
Classifier: Programming Language :: Python :: 3
Requires-Python: ~=3.10
Requires-Dist: contourpy~=1.0.7
Requires-Dist: cycler~=0.11.0
Requires-Dist: fonttools~=4.39.4
Requires-Dist: kiwisolver~=1.4.4
Requires-Dist: matplotlib~=3.7.1
Requires-Dist: numpy~=1.24.3
Requires-Dist: packaging~=23.1
Requires-Dist: pandas~=2.0.2
Requires-Dist: pillow~=9.5.0
Requires-Dist: pyparsing~=3.0.9
Requires-Dist: python-dateutil~=2.8.2
Requires-Dist: pytz~=2023.3
Requires-Dist: scipy~=1.10.1
Requires-Dist: six~=1.16.0
Requires-Dist: tzdata~=2023.3
